cronos/__init__.py
cronos/cli.py
cronos/constants.py
cronos/parser.py
cronosparser-0.2.dist-info/DESCRIPTION.rst
cronosparser-0.2.dist-info/METADATA
cronosparser-0.2.dist-info/RECORD
cronosparser-0.2.dist-info/WHEEL
cronosparser-0.2.dist-info/entry_points.txt
cronosparser-0.2.dist-info/metadata.json
cronosparser-0.2.dist-info/namespace_packages.txt
cronosparser-0.2.dist-info/top_level.txt
