Metadata-Version: 2.0
Name: cronosparser
Version: 0.2
Summary: Parser for CronosPro / CronosPlus database files.
Home-page: http://github.com/occrp/cronosparser
Author: OCCRP
Author-email: tech@occrp.org
License: MIT
Keywords: files walk index survey
Platform: UNKNOWN
Classifier: Development Status :: 3 - Alpha
Classifier: Intended Audience :: Developers
Classifier: License :: OSI Approved :: MIT License
Classifier: Operating System :: OS Independent
Classifier: Programming Language :: Python :: 2.6
Classifier: Programming Language :: Python :: 2.7
Requires-Dist: click
Requires-Dist: normality
Requires-Dist: six
Requires-Dist: unicodecsv
